lambdautil/__init__.py
lambdautil/aws_clients.py
lambdautil/cfg.py
lambdautil/command.py
lambdautil/creator.py
lambdautil/deployer.py
lambdautil/stack.py
lambdautil/utility.py
lambdautil/config_parser/__init__.py
lambdautil/parts/__init__.py
lambdautil/parts/service/__init__.py
lambdautil/parts/simple/__init__.py
lambdautil/template/__init__.py
lambdautil-0.4.5.dist-info/METADATA
lambdautil-0.4.5.dist-info/WHEEL
lambdautil-0.4.5.dist-info/entry_points.txt
lambdautil-0.4.5.dist-info/top_level.txt
lambdautil-0.4.5.dist-info/RECORD
