Metadata-Version: 2.1
Name: lambdautil
Version: 0.4.5
Summary: Python Lambda Utility
Home-page: https://github.com/muckamuck/LambdaUtil
Author: Duke P. Takle
Author-email: duke.takle@gmail.com
Requires-Dist: boto3
Requires-Dist: Click
Requires-Dist: tabulate
Requires-Dist: PyYAML
